qframelesswindow/__init__.py
qframelesswindow/_rc/__init__.py
qframelesswindow/_rc/resource.py
qframelesswindow/linux/__init__.py
qframelesswindow/linux/window_effect.py
qframelesswindow/mac/__init__.py
qframelesswindow/mac/window_effect.py
qframelesswindow/titlebar/__init__.py
qframelesswindow/titlebar/title_bar_buttons.py
qframelesswindow/utils/__init__.py
qframelesswindow/utils/linux_utils.py
qframelesswindow/utils/mac_utils.py
qframelesswindow/utils/win32_utils.py
qframelesswindow/webengine/__init__.py
qframelesswindow/windows/__init__.py
qframelesswindow/windows/c_structures.py
qframelesswindow/windows/window_effect.py
pysidesix_frameless_window-0.7.7.dist-info/LICENSE
pysidesix_frameless_window-0.7.7.dist-info/METADATA
pysidesix_frameless_window-0.7.7.dist-info/WHEEL
pysidesix_frameless_window-0.7.7.dist-info/top_level.txt
pysidesix_frameless_window-0.7.7.dist-info/RECORD
