Metadata-Version: 2.1
Name: PySideSix-Frameless-Window
Version: 0.7.7
Summary: A cross-platform frameless window based on pyside6, support Win32, Linux and macOS.
Home-page: https://github.com/zhiyiYo/PyQt-Frameless-Window/tree/PySide6
Author: zhiyiYo
Author-email: shokokawaii@outlook.com
License: LGPLv3
Keywords: pyside6 frameless
Classifier: Programming Language :: Python :: 3
Classifier: License :: OSI Approved :: GNU Lesser General Public License v3 (LGPLv3)
Classifier: Operating System :: OS Independent
License-File: LICENSE
Requires-Dist: pyobjc ; platform_system == "Darwin"
Requires-Dist: PyCocoa ; platform_system == "Darwin"
Requires-Dist: pywin32 ; platform_system == "Windows"
